gfatypes/__init__.py
gfatypes/gfatypes.py
gfatypes-0.0.2.dist-info/LICENSE
gfatypes-0.0.2.dist-info/METADATA
gfatypes-0.0.2.dist-info/WHEEL
gfatypes-0.0.2.dist-info/top_level.txt
gfatypes-0.0.2.dist-info/RECORD
