Metadata-Version: 2.1
Name: gfatypes
Version: 0.0.2
Summary: Package that packs some utility functions.
Home-page: https://github.com/Tharos-ux/gfatypes
Author: Tharos
Author-email: Tharos <dubois.siegfried@gmail.com>
License: MIT
Project-URL: Homepage, https://github.com/Tharos-ux/gfatypes
Project-URL: Bug Tracker, https://github.com/Tharos-ux/gfatypes/issues
Classifier: Programming Language :: Python :: 3
Classifier: License :: OSI Approved :: MIT License
Classifier: Operating System :: OS Independent
Requires-Python: >=3.10
License-File: LICENSE
